README.txt
setup.py
uvc/__init__.py
uvc/commands.py
uvc/exc.py
uvc/hg.py
uvc/killableprocess.py
uvc/main.py
uvc/path.py
uvc/svn.py
uvc/util.py
uvc/winprocess.py
uvc.egg-info/PKG-INFO
uvc.egg-info/SOURCES.txt
uvc.egg-info/dependency_links.txt
uvc.egg-info/entry_points.txt
uvc.egg-info/requires.txt
uvc.egg-info/top_level.txt
uvc/tests/__init__.py
uvc/tests/mock.py
uvc/tests/test_commands.py
uvc/tests/test_hg.py
uvc/tests/test_main.py
uvc/tests/test_svn.py
uvc/tests/util.py