Metadata-Version: 1.0
Name: uvc
Version: 0.3.2
Summary: The Uber Version Controller. Early release of the version control facade used by Bespin.
Home-page: http://bitbucket.org/dangoor/uvc/
Author: Kevin Dangoor
Author-email: dangoor+uvc@gmail.com
License: MPL/GPL/LGPL
Platform: UNKNOWN
